dd_selenium/__init__.py
dd_selenium-0.0.4.dist-info/LICENSE
dd_selenium-0.0.4.dist-info/METADATA
dd_selenium-0.0.4.dist-info/WHEEL
dd_selenium-0.0.4.dist-info/top_level.txt
dd_selenium-0.0.4.dist-info/RECORD
