Metadata-Version: 2.1
Name: dd-selenium
Version: 0.0.4
Summary: Providing drag and drop functionality in selenium python.
Home-page: https://github.com/leothewolf/dd-selenium
Author: leothewolf
Author-email: doneatease@gmail.com
License: UNKNOWN
Project-URL: Bug Tracker, https://github.com/leothewolf/dd-selenium/issues
Platform: UNKNOWN
Classifier: Programming Language :: Python :: 3
Classifier: License :: OSI Approved :: MIT License
Classifier: Operating System :: OS Independent
Requires-Python: >=3.6
License-File: LICENSE
